pydruglogics/__init__.py
pydruglogics/execution/Executor.py
pydruglogics/execution/__init__.py
pydruglogics/input/ModelOutputs.py
pydruglogics/input/Perturbations.py
pydruglogics/input/TrainingData.py
pydruglogics/input/__init__.py
pydruglogics/model/BooleanModel.py
pydruglogics/model/BooleanModelOptimizer.py
pydruglogics/model/Evolution.py
pydruglogics/model/InteractionModel.py
pydruglogics/model/ModelPredictions.py
pydruglogics/model/__init__.py
pydruglogics/statistics/Statistics.py
pydruglogics/statistics/__init__.py
pydruglogics/utils/BNetworkUtil.py
pydruglogics/utils/Logger.py
pydruglogics/utils/PlotUtil.py
pydruglogics/utils/__init__.py
pydruglogics-0.1.10.dist-info/licenses/LICENSE
tests/__init__.py
tests/executor/Executor_test.py
tests/executor/__init__.py
tests/input/ModelOutputs_test.py
tests/input/Perturbation_test.py
tests/input/TrainingData_test.py
tests/input/__init__.py
tests/model/BooleanModel_test.py
tests/model/Evolution_test.py
tests/model/InteractionModel_test.py
tests/model/ModelPredictions_test.py
tests/model/Statistics_test.py
tests/model/__init__.py
tests/utils/BNetworkUtil_test.py
tests/utils/PlotUtil_test.py
tests/utils/__init__.py
pydruglogics-0.1.10.dist-info/METADATA
pydruglogics-0.1.10.dist-info/WHEEL
pydruglogics-0.1.10.dist-info/top_level.txt
pydruglogics-0.1.10.dist-info/RECORD
