Metadata-Version: 2.4
Name: pydruglogics
Version: 0.1.10
Summary: Constructing, optimizing Boolean Models and performing in-silico perturbations.
Home-page: https://github.com/druglogics/pydruglogics
Author: Laura Szekeres
Author-email: szekereslaura98@gmail.com
License:                     GNU GENERAL PUBLIC LICENSE
Classifier: Programming Language :: Python :: 3
Classifier: License :: OSI Approved :: GNU General Public License v3 (GPLv3)
Classifier: Operating System :: POSIX :: Linux
Classifier: Intended Audience :: Science/Research
Classifier: Topic :: Scientific/Engineering :: Bio-Informatics
Requires-Python: >=3.11
License-File: LICENSE
Requires-Dist: joblib~=1.4.2
Requires-Dist: matplotlib~=3.9.2
Requires-Dist: mpbn~=3.8
Requires-Dist: numpy~=2.1.3
Requires-Dist: pandas~=2.2.3
Requires-Dist: pygad~=3.3.1
Requires-Dist: scikit-learn~=1.5.2
Requires-Dist: scipy~=1.14.1
Provides-Extra: test
Requires-Dist: pytest; extra == "test"
Requires-Dist: pytest-cov; extra == "test"
Dynamic: author-email
Dynamic: home-page
Dynamic: license-file
Dynamic: requires-python
